codekit/__init__.py
codekit/codetools.py
codekit/licensing.py
codekit/cli/__init__.py
codekit/cli/github_auth.py
codekit/cli/github_delete_shadow.py
codekit/cli/github_fork_repos.py
codekit/cli/github_list_repos.py
codekit/cli/github_mv_repos_to_team.py
codekit/cli/github_tag_version.py
codekit/cli/lsst_bp.py
jmatt_sqre_codekit-2.1.0.dist-info/DESCRIPTION.rst
jmatt_sqre_codekit-2.1.0.dist-info/METADATA
jmatt_sqre_codekit-2.1.0.dist-info/RECORD
jmatt_sqre_codekit-2.1.0.dist-info/WHEEL
jmatt_sqre_codekit-2.1.0.dist-info/entry_points.txt
jmatt_sqre_codekit-2.1.0.dist-info/metadata.json
jmatt_sqre_codekit-2.1.0.dist-info/top_level.txt
