Metadata-Version: 2.0
Name: jmatt-sqre-codekit
Version: 2.1.0
Summary: LSST Data Management SQuaRE code management tools
Home-page: https://github.com/lsst-sqre/sqre-codekit
Author: Frossie Economou
Author-email: frossie@lsst.org
License: MIT
Keywords: lsst
Platform: UNKNOWN
Classifier: Development Status :: 4 - Beta
Classifier: Programming Language :: Python :: 2.7
Classifier: Programming Language :: Python :: 3.5
Classifier: Programming Language :: Python :: 3.6
Classifier: License :: OSI Approved :: MIT License
Requires-Dist: GitPython (==1.0.1)
Requires-Dist: MapGitConfig (==1.1)
Requires-Dist: progressbar2 (==3.11.0)
Requires-Dist: requests (>=2.8.1,<3.0.0)
Requires-Dist: sqre-github3.py (==1.0.0a4)
Requires-Dist: sqre-pytravisci (==0.0.3)
Requires-Dist: uritemplate.py (==2.0.0)
Requires-Dist: urllib3 (==1.12)
